fru_parser/__init__.py
fru_parser/cli.py
fru_parser/parser.py
fru_parser-0.1.1.dist-info/METADATA
fru_parser-0.1.1.dist-info/WHEEL
fru_parser-0.1.1.dist-info/entry_points.txt
fru_parser-0.1.1.dist-info/RECORD
