Metadata-Version: 2.4
Name: fru-parser
Version: 0.1.1
Summary:  parses a binary FRU (Field Replaceable Unit) file and extracts information from it.
Author-email: Jack Lin <farwill@gmail.com>
Requires-Python: >=3.9
